metro_turnstile.v
module metro_turnstile(
    input clk,
    input rset,
    input validate_code,
    input [3:0] access_code,  //access pass code
    output reg open_access_door,
    output [1:0] state_out 
);

    //declaration of state values
    parameter [1:0] IDLE = 2'b0,
                    CHECK_CODE = 2'b01,
                    ACCESS_GRANTED = 2'b10;

    //logic for state machines
    reg [1:0] state;
    reg [1:0] next_state;
    reg [3:0] timer;            //counter that keeps the gate open

    //nxt state logic
    always @(*) begin
        next_state = IDLE;
        open_access_door = 0;
        case(state)
            IDLE : begin
                    if(validate_code)
                        next_state = CHECK_CODE;
                    end
            CHECK_CODE : begin
                            if((access_code>=4'd4) && (access_code <= 4'd11))
                                next_state = ACCESS_GRANTED;
                    end
            ACCESS_GRANTED : begin
                                open_access_door = 1;
                                if(timer == 4'hF)
                                    next_state = IDLE;
                                else
                                    next_state = ACCESS_GRANTED;
                    end
            default : next_state = IDLE; //to avoid latch formation or stuck in the FSM
        endcase
    end

    //state sequencer logic and it is similar to pipo register
    always @(posedge clk or negedge rset) begin
        if(!rset)    //active low reset
            state <= IDLE;
        else   
            state <= next_state;
    end

    assign state_out = state;

    //timer logic
    always @(posedge clk or negedge rset) begin
        if(!rset)
            timer <= 0;
        else if (state == ACCESS_GRANTED)
            timer <= timer + 1'b1;
        else
            timer <= 0;
    end
    
endmodule

tb_metro_turnstile.v
`include "metro_turnstile.v"

module tb_metro_turnstile();

    reg clk = 0;
    reg rset;
    reg validate_code;
    reg [3:0] access_code;
    wire open_access_door;
    wire [1:0] state_out;

    metro_turnstile MT(
        .clk(clk),
        .rset(rset),
        .validate_code(validate_code),
        .access_code(access_code),
        .open_access_door(open_access_door),
        .state_out(state_out)
    );

    always #1 clk = ~clk;

    initial begin
        $monitor($time," access_code = %4b,state_out = %2b, open_access_door = %b",
                        access_code,state_out,open_access_door);
        rset = 0; 
        validate_code = 0; access_code = 0;
        #2.5; rset  = 1;
        
        @(posedge clk);
        validate_code = 1; access_code = 0;
        @(posedge clk);
        validate_code = 1; access_code = 0;
        @(posedge clk);
        validate_code = 1; access_code = 9;
        @(posedge clk);
        validate_code = 0; access_code = 9;
        #40; $finish;
    end

    initial begin
        $dumpfile("metro_turnstile.vcd");
        $dumpvars(0,tb_metro_turnstile);
    end

endmodule

metro_turnstile.vcd
$date
	Thu Oct 23 00:24:08 2025
$end
$version
	Icarus Verilog
$end
$timescale
	1s
$end
$scope module tb_metro_turnstile $end
$var wire 2 ! state_out [1:0] $end
$var wire 1 " open_access_door $end
$var reg 4 # access_code [3:0] $end
$var reg 1 $ clk $end
$var reg 1 % rset $end
$var reg 1 & validate_code $end
$scope module MT $end
$var wire 4 ' access_code [3:0] $end
$var wire 1 $ clk $end
$var wire 1 % rset $end
$var wire 2 ( state_out [1:0] $end
$var wire 1 & validate_code $end
$var parameter 2 ) ACCESS_GRANTED $end
$var parameter 2 * CHECK_CODE $end
$var parameter 2 + IDLE $end
$var reg 2 , next_state [1:0] $end
$var reg 1 " open_access_door $end
$var reg 2 - state [1:0] $end
$var reg 4 . timer [3:0] $end
$upscope $end
$upscope $end
$enddefinitions $end
$comment Show the parameter values. $end
$dumpall
b0 +
b1 *
b10 )
$end
#0
$dumpvars
b0 .
b0 -
b0 ,
b0 (
b0 '
0&
0%
0$
b0 #
0"
b0 !
$end
#1
1$
#2
0$
#3
b1 ,
1&
1$
1%
#4
0$
#5
b0 ,
b1 !
b1 (
b1 -
1$
#6
0$
#7
b0 !
b0 (
b0 -
b1 ,
b1001 #
b1001 '
1$
#8
0$
#9
b1 !
b1 (
b1 -
b10 ,
0&
1$
#10
0$
#11
1"
b10 ,
b10 !
b10 (
b10 -
1$
#12
0$
#13
1"
b10 ,
b1 .
1$
#14
0$
#15
1"
b10 ,
b10 .
1$
#16
0$
#17
1"
b10 ,
b11 .
1$
#18
0$
#19
1"
b10 ,
b100 .
1$
#20
0$
#21
1"
b10 ,
b101 .
1$
#22
0$
#23
1"
b10 ,
b110 .
1$
#24
0$
#25
1"
b10 ,
b111 .
1$
#26
0$
#27
1"
b10 ,
b1000 .
1$
#28
0$
#29
1"
b10 ,
b1001 .
1$
#30
0$
#31
1"
b10 ,
b1010 .
1$
#32
0$
#33
1"
b10 ,
b1011 .
1$
#34
0$
#35
1"
b10 ,
b1100 .
1$
#36
0$
#37
1"
b10 ,
b1101 .
1$
#38
0$
#39
1"
b10 ,
b1110 .
1$
#40
0$
#41
1"
b0 ,
b1111 .
1$
#42
0$
#43
0"
b0 !
b0 (
b0 -
b0 .
1$
